build/lib/build/lib/build/lib/build/lib/numexpr_preparser/__init__.py
build/lib/build/lib/build/lib/build/lib/numexpr_preparser/parser.py
build/lib/build/lib/build/lib/build/lib/numexpr_preparser/parser_test.py
build/lib/build/lib/build/lib/numexpr_preparser/__init__.py
build/lib/build/lib/build/lib/numexpr_preparser/parser.py
build/lib/build/lib/build/lib/numexpr_preparser/parser_test.py
build/lib/build/lib/numexpr_preparser/__init__.py
build/lib/build/lib/numexpr_preparser/parser.py
build/lib/build/lib/numexpr_preparser/parser_test.py
build/lib/numexpr_preparser/__init__.py
build/lib/numexpr_preparser/parser.py
build/lib/numexpr_preparser/parser_test.py
numexpr_preparser/__init__.py
numexpr_preparser/parser.py
numexpr_preparser/parser_test.py
numexpr_preparser-1.0.0.dist-info/LICENSE
numexpr_preparser-1.0.0.dist-info/METADATA
numexpr_preparser-1.0.0.dist-info/WHEEL
numexpr_preparser-1.0.0.dist-info/top_level.txt
numexpr_preparser-1.0.0.dist-info/RECORD
