Metadata-Version: 2.1
Name: numexpr-preparser
Version: 1.0.0
Summary: Infix pre-parser/expression validator for numexpr
Author-email: Scott Morken <scottm361@gmail.com>
Project-URL: Homepage, https://github.com/smorken/sphinx_action_example
Project-URL: Bug Tracker, https://github.com/smorken/sphinx_action_example/issues
Classifier: Programming Language :: Python :: 3
Classifier: License :: OSI Approved :: MIT License
Classifier: Operating System :: OS Independent
Requires-Python: >=3.7
License-File: LICENSE
Requires-Dist: numexpr
Requires-Dist: pyparsing
